cv2_enumerate_cameras/__init__.py
cv2_enumerate_cameras/__init__.pyi
cv2_enumerate_cameras/__main__.py
cv2_enumerate_cameras/_windows_backend.pyi
cv2_enumerate_cameras/camera_info.py
cv2_enumerate_cameras/camera_info.pyi
cv2_enumerate_cameras/linux_backend.py
cv2_enumerate_cameras/macos_backend.py
cv2_enumerate_cameras/opencv_backend.py
cv2_enumerate_cameras/py.typed
cv2_enumerate_cameras/windows_backend.py
cv2_enumerate_cameras-1.3.3.dist-info/licenses/LICENSE
cv2_enumerate_cameras-1.3.3.dist-info/METADATA
cv2_enumerate_cameras-1.3.3.dist-info/WHEEL
cv2_enumerate_cameras-1.3.3.dist-info/entry_points.txt
cv2_enumerate_cameras-1.3.3.dist-info/top_level.txt
cv2_enumerate_cameras-1.3.3.dist-info/RECORD
