Metadata-Version: 2.1
Name: cv2_enumerate_cameras
Version: 1.3.3
Summary: Enumerate / List / Find / Detect / Search index for opencv VideoCapture.
Author-email: Yu He <chinaheyu@outlook.com>
License: MIT License
Project-URL: Homepage, https://github.com/lukehugh/cv2_enumerate_cameras
Project-URL: Issues, https://github.com/lukehugh/cv2_enumerate_cameras/issues
Keywords: opencv,cv2,enumerate,camera,video capture
Classifier: Development Status :: 5 - Production/Stable
Classifier: Programming Language :: Python :: 3
Classifier: Programming Language :: Python :: Implementation :: CPython
Classifier: Programming Language :: C++
Classifier: Typing :: Typed
Requires-Python: >=3.6
License-File: LICENSE
Requires-Dist: pyobjc-framework-AVFoundation ; platform_system == "Darwin"
